MultiImport/MainFuncs.py
MultiImport/__init__.py
MultiImport/test.py
MultiImport-1.0.1.dist-info/METADATA
MultiImport-1.0.1.dist-info/WHEEL
MultiImport-1.0.1.dist-info/top_level.txt
MultiImport-1.0.1.dist-info/RECORD
