Metadata-Version: 2.1
Name: MultiImport
Version: 1.0.1
Summary: UNKNOWN
Home-page: UNKNOWN
License: UNKNOWN
Keywords: python,multiimport,multi-import,importlib,importing,import
Platform: UNKNOWN
Requires-Dist: importlib
